{
   "10020" : null,
   "10050" : null,
   "10080" : null,
   "10110" : null,
   "10140" : null,
   "10170" : null,
   "1020" : null,
   "10200" : null,
   "10230" : null,
   "10260" : null,
   "10290" : null,
   "10320" : null,
   "10350" : null,
   "10380" : null,
   "10410" : null,
   "10440" : null,
   "10470" : null,
   "1050" : null,
   "10500" : null,
   "10530" : null,
   "10560" : null,
   "10590" : null,
   "10620" : null,
   "10650" : null,
   "10680" : null,
   "10710" : null,
   "10740" : null,
   "10770" : null,
   "1080" : null,
   "10800" : null,
   "10830" : null,
   "10860" : null,
   "10890" : null,
   "10920" : null,
   "10950" : null,
   "10980" : null,
   "11010" : null,
   "11040" : null,
   "11070" : null,
   "1110" : null,
   "11100" : null,
   "11130" : null,
   "11160" : null,
   "11190" : null,
   "11220" : null,
   "11250" : null,
   "11280" : null,
   "11310" : null,
   "11340" : null,
   "11370" : null,
   "1140" : null,
   "11400" : null,
   "11430" : null,
   "11460" : null,
   "11490" : null,
   "11520" : null,
   "11550" : null,
   "11580" : null,
   "11610" : null,
   "11640" : null,
   "11670" : null,
   "1170" : null,
   "11700" : null,
   "11730" : null,
   "11760" : null,
   "11790" : null,
   "11820" : null,
   "11850" : null,
   "11880" : null,
   "11910" : null,
   "11940" : null,
   "11970" : null,
   "120" : null,
   "1200" : null,
   "12000" : null,
   "12030" : null,
   "12060" : null,
   "12090" : null,
   "12120" : null,
   "12150" : null,
   "12180" : null,
   "12210" : null,
   "12240" : null,
   "12270" : null,
   "1230" : null,
   "12300" : null,
   "12330" : null,
   "12360" : null,
   "12390" : null,
   "12420" : null,
   "12450" : null,
   "12480" : null,
   "12510" : null,
   "12540" : null,
   "12570" : null,
   "1260" : null,
   "12600" : null,
   "12630" : null,
   "12660" : null,
   "12690" : null,
   "12720" : null,
   "12750" : null,
   "12780" : null,
   "12810" : null,
   "12840" : null,
   "12870" : null,
   "1290" : null,
   "12900" : null,
   "12930" : null,
   "12960" : null,
   "12990" : null,
   "13020" : null,
   "13050" : null,
   "13080" : null,
   "13110" : null,
   "13140" : null,
   "13170" : null,
   "1320" : null,
   "13200" : null,
   "13230" : null,
   "13260" : null,
   "13290" : null,
   "13320" : null,
   "13350" : null,
   "13380" : null,
   "13410" : null,
   "13440" : null,
   "13470" : null,
   "1350" : null,
   "13500" : null,
   "13530" : null,
   "13560" : null,
   "13590" : null,
   "13620" : null,
   "13650" : null,
   "13680" : null,
   "13710" : null,
   "13740" : null,
   "13770" : null,
   "1380" : null,
   "13800" : null,
   "13830" : null,
   "13860" : null,
   "13890" : null,
   "13920" : null,
   "13950" : null,
   "13980" : null,
   "14010" : null,
   "14040" : null,
   "14070" : null,
   "1410" : null,
   "14100" : null,
   "14130" : null,
   "14160" : null,
   "14190" : null,
   "14220" : null,
   "14250" : null,
   "14280" : null,
   "14310" : null,
   "14340" : null,
   "14370" : null,
   "1440" : null,
   "14400" : null,
   "14430" : null,
   "14460" : null,
   "14490" : null,
   "14520" : null,
   "14550" : null,
   "14580" : null,
   "14610" : null,
   "14640" : null,
   "14670" : null,
   "1470" : null,
   "14700" : null,
   "14730" : null,
   "14760" : null,
   "14790" : null,
   "14820" : null,
   "14850" : null,
   "14880" : null,
   "14910" : null,
   "14940" : null,
   "14970" : null,
   "150" : null,
   "1500" : null,
   "15000" : null,
   "15030" : null,
   "15060" : null,
   "15090" : null,
   "15120" : null,
   "15150" : null,
   "15180" : null,
   "15210" : null,
   "15240" : null,
   "15270" : null,
   "1530" : null,
   "15300" : null,
   "15330" : null,
   "15360" : null,
   "15390" : null,
   "15420" : null,
   "15450" : null,
   "15480" : null,
   "15510" : null,
   "15540" : null,
   "15570" : null,
   "1560" : null,
   "15600" : null,
   "15630" : null,
   "15660" : null,
   "15690" : null,
   "15720" : null,
   "15750" : null,
   "15780" : null,
   "15810" : null,
   "15840" : null,
   "15870" : null,
   "1590" : null,
   "15900" : null,
   "15930" : null,
   "15960" : null,
   "15990" : null,
   "16020" : null,
   "16050" : null,
   "16080" : null,
   "16110" : null,
   "16140" : null,
   "16170" : null,
   "1620" : null,
   "16200" : null,
   "16230" : null,
   "16260" : null,
   "16290" : null,
   "16320" : null,
   "16350" : null,
   "16380" : null,
   "16410" : null,
   "16440" : null,
   "16470" : null,
   "1650" : null,
   "16500" : null,
   "16530" : null,
   "16560" : null,
   "16590" : null,
   "16620" : null,
   "16650" : null,
   "16680" : null,
   "16710" : null,
   "16740" : null,
   "16770" : null,
   "1680" : null,
   "16800" : null,
   "16830" : null,
   "16860" : null,
   "16890" : null,
   "16920" : null,
   "16950" : null,
   "16980" : null,
   "17010" : null,
   "17040" : null,
   "17070" : null,
   "1710" : null,
   "17100" : null,
   "17130" : null,
   "17160" : null,
   "17190" : null,
   "17220" : null,
   "17250" : null,
   "17280" : null,
   "17310" : null,
   "17340" : null,
   "17370" : null,
   "1740" : null,
   "17400" : null,
   "17430" : null,
   "17460" : null,
   "17490" : null,
   "17520" : null,
   "17550" : null,
   "17580" : null,
   "17610" : null,
   "17640" : null,
   "17670" : null,
   "1770" : null,
   "17700" : null,
   "17730" : null,
   "17760" : null,
   "17790" : null,
   "17820" : null,
   "17850" : null,
   "17880" : null,
   "17910" : null,
   "17940" : null,
   "17970" : null,
   "180" : null,
   "1800" : null,
   "18000" : null,
   "18030" : null,
   "18060" : null,
   "18090" : null,
   "18120" : null,
   "18150" : null,
   "18180" : null,
   "18210" : null,
   "18240" : null,
   "18270" : null,
   "1830" : null,
   "18300" : null,
   "18330" : null,
   "18360" : null,
   "18390" : null,
   "18420" : null,
   "18450" : null,
   "18480" : null,
   "18510" : null,
   "18540" : null,
   "18570" : null,
   "1860" : null,
   "18600" : null,
   "18630" : null,
   "18660" : null,
   "18690" : null,
   "18720" : null,
   "18750" : null,
   "18780" : null,
   "18810" : null,
   "18840" : null,
   "18870" : null,
   "1890" : null,
   "18900" : null,
   "18930" : null,
   "18960" : null,
   "18990" : null,
   "19020" : null,
   "19050" : null,
   "19080" : null,
   "19110" : null,
   "19140" : null,
   "19170" : null,
   "1920" : null,
   "19200" : null,
   "19230" : null,
   "19260" : null,
   "19290" : null,
   "19320" : null,
   "19350" : null,
   "19380" : null,
   "19410" : null,
   "19440" : null,
   "19470" : null,
   "1950" : null,
   "19500" : null,
   "19530" : null,
   "19560" : null,
   "19590" : null,
   "19620" : null,
   "19650" : null,
   "19680" : null,
   "19710" : null,
   "19740" : null,
   "19770" : null,
   "1980" : null,
   "19800" : null,
   "19830" : null,
   "19860" : null,
   "19890" : null,
   "19920" : null,
   "19950" : null,
   "19980" : null,
   "20010" : null,
   "20040" : null,
   "20070" : null,
   "2010" : null,
   "20100" : null,
   "20130" : null,
   "20160" : null,
   "20190" : null,
   "20220" : null,
   "20250" : null,
   "20280" : null,
   "20310" : null,
   "20340" : null,
   "20370" : null,
   "2040" : null,
   "20400" : null,
   "20430" : null,
   "20460" : null,
   "20490" : null,
   "20520" : null,
   "20550" : null,
   "20580" : null,
   "20610" : null,
   "20640" : null,
   "20670" : null,
   "2070" : null,
   "20700" : null,
   "20730" : null,
   "20760" : null,
   "20790" : null,
   "20820" : null,
   "20850" : null,
   "20880" : null,
   "20910" : null,
   "20940" : null,
   "20970" : null,
   "210" : null,
   "2100" : null,
   "21000" : null,
   "21030" : null,
   "21060" : null,
   "21090" : null,
   "21120" : null,
   "21150" : null,
   "21180" : null,
   "21210" : null,
   "21240" : null,
   "21270" : null,
   "2130" : null,
   "21300" : null,
   "21330" : null,
   "21360" : null,
   "21390" : null,
   "21420" : null,
   "21450" : null,
   "21480" : null,
   "21510" : null,
   "21540" : null,
   "21570" : null,
   "2160" : null,
   "21600" : null,
   "21630" : null,
   "21660" : null,
   "21690" : null,
   "21720" : null,
   "21750" : null,
   "21780" : null,
   "21810" : null,
   "21840" : null,
   "21870" : null,
   "2190" : null,
   "21900" : null,
   "21930" : null,
   "21960" : null,
   "21990" : null,
   "22020" : null,
   "22050" : null,
   "22080" : null,
   "22110" : null,
   "22140" : null,
   "22170" : null,
   "2220" : null,
   "22200" : null,
   "22230" : null,
   "22260" : null,
   "22290" : null,
   "22320" : null,
   "22350" : null,
   "22380" : null,
   "22410" : null,
   "22440" : null,
   "22470" : null,
   "2250" : null,
   "22500" : null,
   "22530" : null,
   "22560" : null,
   "22590" : null,
   "22620" : null,
   "22650" : null,
   "22680" : null,
   "22710" : null,
   "22740" : null,
   "22770" : null,
   "2280" : null,
   "22800" : null,
   "22830" : null,
   "22860" : null,
   "22890" : null,
   "22920" : null,
   "22950" : null,
   "22980" : null,
   "23010" : null,
   "23040" : null,
   "23070" : null,
   "2310" : null,
   "23100" : null,
   "23130" : null,
   "23160" : null,
   "23190" : null,
   "23220" : null,
   "23250" : null,
   "23280" : null,
   "23310" : null,
   "23340" : null,
   "23370" : null,
   "2340" : null,
   "23400" : null,
   "23430" : null,
   "23460" : null,
   "23490" : null,
   "23520" : null,
   "23550" : null,
   "23580" : null,
   "23610" : null,
   "23640" : null,
   "23670" : null,
   "2370" : null,
   "23700" : null,
   "23730" : null,
   "23760" : null,
   "23790" : null,
   "23820" : null,
   "23850" : null,
   "23880" : null,
   "23910" : null,
   "23940" : null,
   "23970" : null,
   "240" : null,
   "2400" : null,
   "24000" : null,
   "24030" : null,
   "24060" : null,
   "24090" : null,
   "24120" : null,
   "24150" : null,
   "24180" : null,
   "24210" : null,
   "24240" : null,
   "24270" : null,
   "2430" : null,
   "24300" : null,
   "24330" : null,
   "24360" : null,
   "24390" : null,
   "24420" : null,
   "24450" : null,
   "24480" : null,
   "24510" : null,
   "24540" : null,
   "24570" : null,
   "2460" : null,
   "24600" : null,
   "24630" : null,
   "24660" : null,
   "24690" : null,
   "24720" : null,
   "24750" : null,
   "24780" : null,
   "24810" : null,
   "24840" : null,
   "24870" : null,
   "2490" : null,
   "24900" : null,
   "24930" : null,
   "24960" : null,
   "24990" : null,
   "25020" : null,
   "25050" : null,
   "25080" : null,
   "25110" : null,
   "25140" : null,
   "25170" : null,
   "2520" : null,
   "25200" : null,
   "25230" : null,
   "25260" : null,
   "25290" : null,
   "25320" : null,
   "25350" : null,
   "25380" : null,
   "25410" : null,
   "25440" : null,
   "25470" : null,
   "2550" : null,
   "25500" : null,
   "25530" : null,
   "25560" : null,
   "25590" : null,
   "25620" : null,
   "25650" : null,
   "25680" : null,
   "25710" : null,
   "25740" : null,
   "25770" : null,
   "2580" : null,
   "25800" : null,
   "25830" : null,
   "25860" : null,
   "25890" : null,
   "25920" : null,
   "25950" : null,
   "25980" : null,
   "26010" : null,
   "26040" : null,
   "26070" : null,
   "2610" : null,
   "26100" : null,
   "26130" : null,
   "26160" : null,
   "26190" : null,
   "26220" : null,
   "26250" : null,
   "26280" : null,
   "26310" : null,
   "26340" : null,
   "26370" : null,
   "2640" : null,
   "26400" : null,
   "26430" : null,
   "26460" : null,
   "26490" : null,
   "26520" : null,
   "26550" : null,
   "26580" : null,
   "26610" : null,
   "26640" : null,
   "26670" : null,
   "2670" : null,
   "26700" : null,
   "26730" : null,
   "26760" : null,
   "26790" : null,
   "26820" : null,
   "26850" : null,
   "26880" : null,
   "26910" : null,
   "26940" : null,
   "26970" : null,
   "270" : null,
   "2700" : null,
   "27000" : null,
   "27030" : null,
   "27060" : null,
   "27090" : null,
   "27120" : null,
   "27150" : null,
   "27180" : null,
   "27210" : null,
   "27240" : null,
   "27270" : null,
   "2730" : null,
   "27300" : null,
   "27330" : null,
   "27360" : null,
   "27390" : null,
   "27420" : null,
   "27450" : null,
   "27480" : null,
   "27510" : null,
   "27540" : null,
   "27570" : null,
   "2760" : null,
   "27600" : null,
   "27630" : null,
   "27660" : null,
   "27690" : null,
   "27720" : null,
   "27750" : null,
   "27780" : null,
   "27810" : null,
   "27840" : null,
   "27870" : null,
   "2790" : null,
   "27900" : null,
   "27930" : null,
   "27960" : null,
   "27990" : null,
   "28020" : null,
   "28050" : null,
   "28080" : null,
   "28110" : null,
   "28140" : null,
   "28170" : null,
   "2820" : null,
   "28200" : null,
   "28230" : null,
   "28260" : null,
   "28290" : null,
   "28320" : null,
   "28350" : null,
   "28380" : null,
   "28410" : null,
   "28440" : null,
   "28470" : null,
   "2850" : null,
   "28500" : null,
   "28530" : null,
   "28560" : null,
   "28590" : null,
   "28620" : null,
   "28650" : null,
   "28680" : null,
   "28710" : null,
   "28740" : null,
   "28770" : null,
   "2880" : null,
   "28800" : null,
   "28830" : null,
   "28860" : null,
   "28890" : null,
   "28920" : null,
   "28950" : null,
   "28980" : null,
   "29010" : null,
   "29040" : null,
   "29070" : null,
   "2910" : null,
   "29100" : null,
   "29130" : null,
   "29160" : null,
   "29190" : null,
   "29220" : null,
   "29250" : null,
   "29280" : null,
   "29310" : null,
   "29340" : null,
   "29370" : null,
   "2940" : null,
   "29400" : null,
   "29430" : null,
   "29460" : null,
   "29490" : null,
   "29520" : null,
   "29550" : null,
   "29580" : null,
   "29610" : null,
   "29640" : null,
   "29670" : null,
   "2970" : null,
   "29700" : null,
   "29730" : null,
   "29760" : null,
   "29790" : null,
   "29820" : null,
   "29850" : null,
   "29880" : null,
   "29910" : null,
   "29940" : null,
   "29970" : null,
   "30" : null,
   "300" : null,
   "3000" : null,
   "30000" : null,
   "30030" : null,
   "30060" : null,
   "30090" : null,
   "30120" : null,
   "30150" : null,
   "30180" : null,
   "30210" : null,
   "30240" : null,
   "30270" : null,
   "3030" : null,
   "30300" : null,
   "30330" : null,
   "30360" : null,
   "30390" : null,
   "30420" : null,
   "30450" : null,
   "30480" : null,
   "30510" : null,
   "30540" : null,
   "30570" : null,
   "3060" : null,
   "30600" : null,
   "30630" : null,
   "30660" : null,
   "30690" : null,
   "30720" : null,
   "30750" : null,
   "30780" : null,
   "30810" : null,
   "30840" : null,
   "30870" : null,
   "3090" : null,
   "30900" : null,
   "30930" : null,
   "30960" : null,
   "30990" : null,
   "31020" : null,
   "31050" : null,
   "31080" : null,
   "31110" : null,
   "31140" : null,
   "31170" : null,
   "3120" : null,
   "31200" : null,
   "31230" : null,
   "31260" : null,
   "31290" : null,
   "31320" : null,
   "31350" : null,
   "31380" : null,
   "31410" : null,
   "31440" : null,
   "31470" : null,
   "3150" : null,
   "31500" : null,
   "31530" : null,
   "31560" : null,
   "31590" : null,
   "31620" : null,
   "31650" : null,
   "31680" : null,
   "31710" : null,
   "31740" : null,
   "31770" : null,
   "3180" : null,
   "31800" : null,
   "31830" : null,
   "31860" : null,
   "31890" : null,
   "31920" : null,
   "31950" : null,
   "31980" : null,
   "32010" : null,
   "32040" : null,
   "32070" : null,
   "3210" : null,
   "32100" : null,
   "32130" : null,
   "32160" : null,
   "32190" : null,
   "32220" : null,
   "32250" : null,
   "32280" : null,
   "32310" : null,
   "32340" : null,
   "32370" : null,
   "3240" : null,
   "32400" : null,
   "32430" : null,
   "32460" : null,
   "32490" : null,
   "32520" : null,
   "32550" : null,
   "32580" : null,
   "32610" : null,
   "32640" : null,
   "32670" : null,
   "3270" : null,
   "32700" : null,
   "32730" : null,
   "32760" : null,
   "32790" : null,
   "32820" : null,
   "32850" : null,
   "32880" : null,
   "32910" : null,
   "32940" : null,
   "32970" : null,
   "330" : null,
   "3300" : null,
   "33000" : null,
   "33030" : null,
   "33060" : null,
   "33090" : null,
   "33120" : null,
   "33150" : null,
   "33180" : null,
   "33210" : null,
   "33240" : null,
   "33270" : null,
   "3330" : null,
   "33300" : null,
   "33330" : null,
   "33360" : null,
   "33390" : null,
   "33420" : null,
   "33450" : null,
   "33480" : null,
   "33510" : null,
   "33540" : null,
   "33570" : null,
   "3360" : null,
   "33600" : null,
   "33630" : null,
   "33660" : null,
   "33690" : null,
   "33720" : null,
   "33750" : null,
   "33780" : null,
   "33810" : null,
   "33840" : null,
   "33870" : null,
   "3390" : null,
   "33900" : null,
   "33930" : null,
   "33960" : null,
   "33990" : null,
   "34020" : null,
   "34050" : null,
   "34080" : null,
   "34110" : null,
   "34140" : null,
   "34170" : null,
   "3420" : null,
   "34200" : null,
   "34230" : null,
   "34260" : null,
   "34290" : null,
   "34320" : null,
   "34350" : null,
   "34380" : null,
   "34410" : null,
   "34440" : null,
   "34470" : null,
   "3450" : null,
   "34500" : null,
   "34530" : null,
   "34560" : null,
   "34590" : null,
   "34620" : null,
   "34650" : null,
   "34680" : null,
   "34710" : null,
   "34740" : null,
   "34770" : null,
   "3480" : null,
   "34800" : null,
   "34830" : null,
   "34860" : null,
   "34890" : null,
   "34920" : null,
   "34950" : null,
   "34980" : null,
   "35010" : null,
   "35040" : null,
   "35070" : null,
   "3510" : null,
   "35100" : null,
   "35130" : null,
   "35160" : null,
   "35190" : null,
   "35220" : null,
   "35250" : null,
   "35280" : null,
   "35310" : null,
   "35340" : null,
   "35370" : null,
   "3540" : null,
   "35400" : null,
   "35430" : null,
   "35460" : null,
   "35490" : null,
   "35520" : null,
   "35550" : null,
   "35580" : null,
   "35610" : null,
   "35640" : null,
   "35670" : null,
   "3570" : null,
   "35700" : null,
   "35730" : null,
   "35760" : null,
   "35790" : null,
   "35820" : null,
   "35850" : null,
   "35880" : null,
   "35910" : null,
   "35940" : null,
   "35970" : null,
   "360" : null,
   "3600" : null,
   "36000" : null,
   "36030" : null,
   "36060" : null,
   "36090" : null,
   "36120" : null,
   "36150" : null,
   "36180" : null,
   "36210" : null,
   "36240" : null,
   "36270" : null,
   "3630" : null,
   "36300" : null,
   "36330" : null,
   "36360" : null,
   "36390" : null,
   "36420" : null,
   "36450" : null,
   "36480" : null,
   "36510" : null,
   "36540" : null,
   "36570" : null,
   "3660" : null,
   "36600" : null,
   "36630" : null,
   "36660" : null,
   "36690" : null,
   "36720" : null,
   "36750" : null,
   "36780" : null,
   "36810" : null,
   "36840" : null,
   "36870" : null,
   "3690" : null,
   "36900" : null,
   "36930" : null,
   "36960" : null,
   "36990" : null,
   "37020" : null,
   "37050" : null,
   "37080" : null,
   "37110" : null,
   "37140" : null,
   "37170" : null,
   "3720" : null,
   "37200" : null,
   "37230" : null,
   "37260" : null,
   "37290" : null,
   "37320" : null,
   "37350" : null,
   "37380" : null,
   "37410" : null,
   "37440" : null,
   "37470" : null,
   "3750" : null,
   "37500" : null,
   "37530" : null,
   "37560" : null,
   "37590" : null,
   "37620" : null,
   "37650" : null,
   "37680" : null,
   "37710" : null,
   "37740" : null,
   "37770" : null,
   "3780" : null,
   "37800" : null,
   "37830" : null,
   "37860" : null,
   "37890" : null,
   "37920" : null,
   "37950" : null,
   "37980" : null,
   "38010" : null,
   "38040" : null,
   "38070" : null,
   "3810" : null,
   "38100" : null,
   "38130" : null,
   "38160" : null,
   "38190" : null,
   "38220" : null,
   "38250" : null,
   "38280" : null,
   "38310" : null,
   "38340" : null,
   "38370" : null,
   "3840" : null,
   "38400" : null,
   "38430" : null,
   "38460" : null,
   "38490" : null,
   "38520" : null,
   "38550" : null,
   "38580" : null,
   "38610" : null,
   "38640" : null,
   "38670" : null,
   "3870" : null,
   "38700" : null,
   "38730" : null,
   "38760" : null,
   "38790" : null,
   "38820" : null,
   "38850" : null,
   "38880" : null,
   "38910" : null,
   "38940" : null,
   "38970" : null,
   "390" : null,
   "3900" : null,
   "39000" : null,
   "39030" : null,
   "39060" : null,
   "39090" : null,
   "39120" : null,
   "39150" : null,
   "39180" : null,
   "39210" : null,
   "39240" : null,
   "39270" : null,
   "3930" : null,
   "39300" : null,
   "39330" : null,
   "39360" : null,
   "39390" : null,
   "39420" : null,
   "39450" : null,
   "39480" : null,
   "39510" : null,
   "39540" : null,
   "39570" : null,
   "3960" : null,
   "39600" : null,
   "39630" : null,
   "39660" : null,
   "39690" : null,
   "39720" : null,
   "39750" : null,
   "39780" : null,
   "39810" : null,
   "39840" : null,
   "39870" : null,
   "3990" : null,
   "39900" : null,
   "39930" : null,
   "39960" : null,
   "39990" : null,
   "40020" : null,
   "40050" : null,
   "40080" : null,
   "40110" : null,
   "40140" : null,
   "40170" : null,
   "4020" : null,
   "40200" : null,
   "40230" : null,
   "40260" : null,
   "40290" : null,
   "40320" : null,
   "40350" : null,
   "40380" : null,
   "40410" : null,
   "40440" : null,
   "40470" : null,
   "4050" : null,
   "40500" : null,
   "40530" : null,
   "40560" : null,
   "40590" : null,
   "40620" : null,
   "40650" : null,
   "40680" : null,
   "40710" : null,
   "40740" : null,
   "40770" : null,
   "4080" : null,
   "40800" : null,
   "40830" : null,
   "40860" : null,
   "40890" : null,
   "40920" : null,
   "40950" : null,
   "40980" : null,
   "41010" : null,
   "41040" : null,
   "41070" : null,
   "4110" : null,
   "41100" : null,
   "41130" : null,
   "41160" : null,
   "41190" : null,
   "41220" : null,
   "41250" : null,
   "41280" : null,
   "41310" : null,
   "41340" : null,
   "41370" : null,
   "4140" : null,
   "41400" : null,
   "41430" : null,
   "41460" : null,
   "41490" : null,
   "41520" : null,
   "41550" : null,
   "41580" : null,
   "41610" : null,
   "41640" : null,
   "41670" : null,
   "4170" : null,
   "41700" : null,
   "41730" : null,
   "41760" : null,
   "41790" : null,
   "41820" : null,
   "41850" : null,
   "41880" : null,
   "41910" : null,
   "41940" : null,
   "41970" : null,
   "420" : null,
   "4200" : null,
   "42000" : null,
   "42030" : null,
   "42060" : null,
   "42090" : null,
   "42120" : null,
   "42150" : null,
   "42180" : null,
   "42210" : null,
   "42240" : null,
   "42270" : null,
   "4230" : null,
   "42300" : null,
   "42330" : null,
   "42360" : null,
   "42390" : null,
   "42420" : null,
   "42450" : null,
   "42480" : null,
   "42510" : null,
   "42540" : null,
   "42570" : null,
   "4260" : null,
   "42600" : null,
   "42630" : null,
   "42660" : null,
   "42690" : null,
   "42720" : null,
   "42750" : null,
   "42780" : null,
   "42810" : null,
   "42840" : null,
   "42870" : null,
   "4290" : null,
   "42900" : null,
   "42930" : null,
   "42960" : null,
   "42990" : null,
   "43020" : null,
   "43050" : null,
   "43080" : null,
   "43110" : null,
   "43140" : null,
   "43170" : null,
   "4320" : null,
   "43200" : null,
   "43230" : null,
   "43260" : null,
   "43290" : null,
   "43320" : null,
   "43350" : null,
   "43380" : null,
   "43410" : null,
   "43440" : null,
   "43470" : null,
   "4350" : null,
   "43500" : null,
   "43530" : null,
   "43560" : null,
   "43590" : null,
   "43620" : null,
   "43650" : null,
   "43680" : null,
   "43710" : null,
   "43740" : null,
   "43770" : null,
   "4380" : null,
   "43800" : null,
   "43830" : null,
   "43860" : null,
   "43890" : null,
   "43920" : null,
   "43950" : null,
   "43980" : null,
   "44010" : null,
   "44040" : null,
   "44070" : null,
   "4410" : null,
   "44100" : null,
   "44130" : null,
   "44160" : null,
   "44190" : null,
   "44220" : null,
   "44250" : null,
   "44280" : null,
   "44310" : null,
   "44340" : null,
   "44370" : null,
   "4440" : null,
   "44400" : null,
   "44430" : null,
   "44460" : null,
   "44490" : null,
   "44520" : null,
   "44550" : null,
   "44580" : null,
   "44610" : null,
   "44640" : null,
   "44670" : null,
   "4470" : null,
   "44700" : null,
   "44730" : null,
   "44760" : null,
   "44790" : null,
   "44820" : null,
   "44850" : null,
   "44880" : null,
   "44910" : null,
   "44940" : null,
   "44970" : null,
   "450" : null,
   "4500" : null,
   "45000" : null,
   "45030" : null,
   "45060" : null,
   "45090" : null,
   "45120" : null,
   "45150" : null,
   "45180" : null,
   "45210" : null,
   "45240" : null,
   "45270" : null,
   "4530" : null,
   "45300" : null,
   "45330" : null,
   "45360" : null,
   "45390" : null,
   "45420" : null,
   "45450" : null,
   "45480" : null,
   "45510" : null,
   "45540" : null,
   "45570" : null,
   "4560" : null,
   "45600" : null,
   "45630" : null,
   "45660" : null,
   "45690" : null,
   "45720" : null,
   "45750" : null,
   "45780" : null,
   "45810" : null,
   "45840" : null,
   "45870" : null,
   "4590" : null,
   "45900" : null,
   "45930" : null,
   "45960" : null,
   "45990" : null,
   "46020" : null,
   "46050" : null,
   "46080" : null,
   "46110" : null,
   "46140" : null,
   "46170" : null,
   "4620" : null,
   "46200" : null,
   "46230" : null,
   "46260" : null,
   "46290" : null,
   "46320" : null,
   "46350" : null,
   "46380" : null,
   "46410" : null,
   "46440" : null,
   "46470" : null,
   "4650" : null,
   "46500" : null,
   "46530" : null,
   "46560" : null,
   "46590" : null,
   "46620" : null,
   "46650" : null,
   "46680" : null,
   "46710" : null,
   "46740" : null,
   "46770" : null,
   "4680" : null,
   "46800" : null,
   "46830" : null,
   "46860" : null,
   "46890" : null,
   "46920" : null,
   "46950" : null,
   "46980" : null,
   "47010" : null,
   "47040" : null,
   "47070" : null,
   "4710" : null,
   "47100" : null,
   "47130" : null,
   "47160" : null,
   "47190" : null,
   "47220" : null,
   "47250" : null,
   "47280" : null,
   "47310" : null,
   "47340" : null,
   "47370" : null,
   "4740" : null,
   "47400" : null,
   "47430" : null,
   "47460" : null,
   "47490" : null,
   "47520" : null,
   "47550" : null,
   "47580" : null,
   "47610" : null,
   "47640" : null,
   "47670" : null,
   "4770" : null,
   "47700" : null,
   "47730" : null,
   "47760" : null,
   "47790" : null,
   "47820" : null,
   "47850" : null,
   "47880" : null,
   "47910" : null,
   "47940" : null,
   "47970" : null,
   "480" : null,
   "4800" : null,
   "48000" : null,
   "48030" : null,
   "48060" : null,
   "48090" : null,
   "48120" : null,
   "48150" : null,
   "48180" : null,
   "48210" : null,
   "48240" : null,
   "48270" : null,
   "4830" : null,
   "48300" : null,
   "48330" : null,
   "48360" : null,
   "48390" : null,
   "48420" : null,
   "48450" : null,
   "48480" : null,
   "48510" : null,
   "48540" : null,
   "48570" : null,
   "4860" : null,
   "48600" : null,
   "48630" : null,
   "48660" : null,
   "48690" : null,
   "48720" : null,
   "48750" : null,
   "48780" : null,
   "48810" : null,
   "48840" : null,
   "48870" : null,
   "4890" : null,
   "48900" : null,
   "48930" : null,
   "48960" : null,
   "48990" : null,
   "49020" : null,
   "49050" : null,
   "49080" : null,
   "49110" : null,
   "49140" : null,
   "49170" : null,
   "4920" : null,
   "49200" : null,
   "49230" : null,
   "49260" : null,
   "49290" : null,
   "49320" : null,
   "49350" : null,
   "49380" : null,
   "49410" : null,
   "49440" : null,
   "49470" : null,
   "4950" : null,
   "49500" : null,
   "49530" : null,
   "49560" : null,
   "49590" : null,
   "49620" : null,
   "49650" : null,
   "49680" : null,
   "49710" : null,
   "49740" : null,
   "49770" : null,
   "4980" : null,
   "49800" : null,
   "49830" : null,
   "49860" : null,
   "49890" : null,
   "49920" : null,
   "49950" : null,
   "49980" : null,
   "50010" : null,
   "50040" : null,
   "50070" : null,
   "5010" : null,
   "50100" : null,
   "50130" : null,
   "50160" : null,
   "50190" : null,
   "50220" : null,
   "50250" : null,
   "50280" : null,
   "50310" : null,
   "50340" : null,
   "50370" : null,
   "5040" : null,
   "50400" : null,
   "50430" : null,
   "50460" : null,
   "50490" : null,
   "50520" : null,
   "50550" : null,
   "50580" : null,
   "50610" : null,
   "50640" : null,
   "50670" : null,
   "5070" : null,
   "50700" : null,
   "50730" : null,
   "50760" : null,
   "50790" : null,
   "50820" : null,
   "50850" : null,
   "50880" : null,
   "50910" : null,
   "50940" : null,
   "50970" : null,
   "510" : null,
   "5100" : null,
   "51000" : null,
   "51030" : null,
   "51060" : null,
   "51090" : null,
   "51120" : null,
   "51150" : null,
   "51180" : null,
   "51210" : null,
   "51240" : null,
   "51270" : null,
   "5130" : null,
   "51300" : null,
   "51330" : null,
   "51360" : null,
   "51390" : null,
   "51420" : null,
   "51450" : null,
   "51480" : null,
   "51510" : null,
   "51540" : null,
   "51570" : null,
   "5160" : null,
   "51600" : null,
   "51630" : null,
   "51660" : null,
   "51690" : null,
   "51720" : null,
   "51750" : null,
   "51780" : null,
   "51810" : null,
   "51840" : null,
   "51870" : null,
   "5190" : null,
   "51900" : null,
   "51930" : null,
   "51960" : null,
   "51990" : null,
   "52020" : null,
   "52050" : null,
   "52080" : null,
   "52110" : null,
   "52140" : null,
   "52170" : null,
   "5220" : null,
   "52200" : null,
   "52230" : null,
   "52260" : null,
   "52290" : null,
   "52320" : null,
   "52350" : null,
   "52380" : null,
   "52410" : null,
   "52440" : null,
   "52470" : null,
   "5250" : null,
   "52500" : null,
   "52530" : null,
   "52560" : null,
   "52590" : null,
   "52620" : null,
   "52650" : null,
   "52680" : null,
   "52710" : null,
   "52740" : null,
   "52770" : null,
   "5280" : null,
   "52800" : null,
   "52830" : null,
   "52860" : null,
   "52890" : null,
   "52920" : null,
   "52950" : null,
   "52980" : null,
   "53010" : null,
   "53040" : null,
   "53070" : null,
   "5310" : null,
   "53100" : null,
   "53130" : null,
   "53160" : null,
   "53190" : null,
   "53220" : null,
   "53250" : null,
   "53280" : null,
   "53310" : null,
   "53340" : null,
   "53370" : null,
   "5340" : null,
   "53400" : null,
   "53430" : null,
   "53460" : null,
   "53490" : null,
   "53520" : null,
   "53550" : null,
   "53580" : null,
   "53610" : null,
   "53640" : null,
   "53670" : null,
   "5370" : null,
   "53700" : null,
   "53730" : null,
   "53760" : null,
   "53790" : null,
   "53820" : null,
   "53850" : null,
   "53880" : null,
   "53910" : null,
   "53940" : null,
   "53970" : null,
   "540" : null,
   "5400" : null,
   "54000" : null,
   "54030" : null,
   "54060" : null,
   "54090" : null,
   "54120" : null,
   "54150" : null,
   "54180" : null,
   "54210" : null,
   "54240" : null,
   "54270" : null,
   "5430" : null,
   "54300" : null,
   "54330" : null,
   "54360" : null,
   "54390" : null,
   "54420" : null,
   "54450" : null,
   "54480" : null,
   "54510" : null,
   "54540" : null,
   "54570" : null,
   "5460" : null,
   "54600" : null,
   "54630" : null,
   "54660" : null,
   "54690" : null,
   "54720" : null,
   "54750" : null,
   "54780" : null,
   "54810" : null,
   "54840" : null,
   "54870" : null,
   "5490" : null,
   "54900" : null,
   "54930" : null,
   "54960" : null,
   "54990" : null,
   "55020" : null,
   "55050" : null,
   "55080" : null,
   "55110" : null,
   "55140" : null,
   "55170" : null,
   "5520" : null,
   "55200" : null,
   "55230" : null,
   "55260" : null,
   "55290" : null,
   "55320" : null,
   "55350" : null,
   "55380" : null,
   "55410" : null,
   "55440" : null,
   "55470" : null,
   "5550" : null,
   "55500" : null,
   "55530" : null,
   "55560" : null,
   "55590" : null,
   "55620" : null,
   "55650" : null,
   "55680" : null,
   "55710" : null,
   "55740" : null,
   "55770" : null,
   "5580" : null,
   "55800" : null,
   "55830" : null,
   "55860" : null,
   "55890" : null,
   "55920" : null,
   "55950" : null,
   "55980" : null,
   "56010" : null,
   "56040" : null,
   "56070" : null,
   "5610" : null,
   "56100" : null,
   "56130" : null,
   "56160" : null,
   "56190" : null,
   "56220" : null,
   "56250" : null,
   "56280" : null,
   "56310" : null,
   "56340" : null,
   "56370" : null,
   "5640" : null,
   "56400" : null,
   "56430" : null,
   "56460" : null,
   "56490" : null,
   "56520" : null,
   "56550" : null,
   "56580" : null,
   "56610" : null,
   "56640" : null,
   "56670" : null,
   "5670" : null,
   "56700" : null,
   "56730" : null,
   "56760" : null,
   "56790" : null,
   "56820" : null,
   "56850" : null,
   "56880" : null,
   "56910" : null,
   "56940" : null,
   "56970" : null,
   "570" : null,
   "5700" : null,
   "57000" : null,
   "57030" : null,
   "57060" : null,
   "57090" : null,
   "57120" : null,
   "57150" : null,
   "57180" : null,
   "57210" : null,
   "57240" : null,
   "57270" : null,
   "5730" : null,
   "57300" : null,
   "57330" : null,
   "57360" : null,
   "57390" : null,
   "57420" : null,
   "57450" : null,
   "57480" : null,
   "57510" : null,
   "57540" : null,
   "57570" : null,
   "5760" : null,
   "57600" : null,
   "57630" : null,
   "57660" : null,
   "57690" : null,
   "57720" : null,
   "57750" : null,
   "57780" : null,
   "57810" : null,
   "57840" : null,
   "57870" : null,
   "5790" : null,
   "57900" : null,
   "57930" : null,
   "57960" : null,
   "57990" : null,
   "58020" : null,
   "58050" : null,
   "58080" : null,
   "58110" : null,
   "58140" : null,
   "58170" : null,
   "5820" : null,
   "58200" : null,
   "58230" : null,
   "58260" : null,
   "58290" : null,
   "58320" : null,
   "58350" : null,
   "58380" : null,
   "58410" : null,
   "58440" : null,
   "58470" : null,
   "5850" : null,
   "58500" : null,
   "58530" : null,
   "58560" : null,
   "58590" : null,
   "58620" : null,
   "58650" : null,
   "58680" : null,
   "58710" : null,
   "58740" : null,
   "58770" : null,
   "5880" : null,
   "58800" : null,
   "58830" : null,
   "58860" : null,
   "58890" : null,
   "58920" : null,
   "58950" : null,
   "58980" : null,
   "59010" : null,
   "59040" : null,
   "59070" : null,
   "5910" : null,
   "59100" : null,
   "59130" : null,
   "59160" : null,
   "59190" : null,
   "59220" : null,
   "59250" : null,
   "59280" : null,
   "59310" : null,
   "59340" : null,
   "59370" : null,
   "5940" : null,
   "59400" : null,
   "59430" : null,
   "59460" : null,
   "59490" : null,
   "59520" : null,
   "59550" : null,
   "59580" : null,
   "59610" : null,
   "59640" : null,
   "59670" : null,
   "5970" : null,
   "59700" : null,
   "59730" : null,
   "59760" : null,
   "59790" : null,
   "59820" : null,
   "59850" : null,
   "59880" : null,
   "59910" : null,
   "59940" : null,
   "59970" : null,
   "60" : null,
   "600" : null,
   "6000" : null,
   "60000" : null,
   "60030" : null,
   "60060" : null,
   "60090" : null,
   "60120" : null,
   "60150" : null,
   "60180" : null,
   "60210" : null,
   "60240" : null,
   "60270" : null,
   "6030" : null,
   "60300" : null,
   "60330" : null,
   "60360" : null,
   "60390" : null,
   "60420" : null,
   "60450" : null,
   "60480" : null,
   "60510" : null,
   "60540" : null,
   "60570" : null,
   "6060" : null,
   "60600" : null,
   "60630" : null,
   "60660" : null,
   "60690" : null,
   "60720" : null,
   "60750" : null,
   "60780" : null,
   "60810" : null,
   "60840" : null,
   "60870" : null,
   "6090" : null,
   "60900" : null,
   "60930" : null,
   "60960" : null,
   "60990" : null,
   "61020" : null,
   "61050" : null,
   "61080" : null,
   "61110" : null,
   "61140" : null,
   "61170" : null,
   "6120" : null,
   "61200" : null,
   "61230" : null,
   "61260" : null,
   "61290" : null,
   "61320" : null,
   "61350" : null,
   "61380" : null,
   "61410" : null,
   "61440" : null,
   "61470" : null,
   "6150" : null,
   "61500" : null,
   "61530" : null,
   "61560" : null,
   "61590" : null,
   "61620" : null,
   "61650" : null,
   "61680" : null,
   "61710" : null,
   "61740" : null,
   "61770" : null,
   "6180" : null,
   "61800" : null,
   "61830" : null,
   "61860" : null,
   "61890" : null,
   "61920" : null,
   "61950" : null,
   "61980" : null,
   "62010" : null,
   "62040" : null,
   "62070" : null,
   "6210" : null,
   "62100" : null,
   "62130" : null,
   "62160" : null,
   "62190" : null,
   "62220" : null,
   "62250" : null,
   "62280" : null,
   "62310" : null,
   "62340" : null,
   "62370" : null,
   "6240" : null,
   "62400" : null,
   "62430" : null,
   "62460" : null,
   "62490" : null,
   "62520" : null,
   "62550" : null,
   "62580" : null,
   "62610" : null,
   "62640" : null,
   "62670" : null,
   "6270" : null,
   "62700" : null,
   "62730" : null,
   "62760" : null,
   "62790" : null,
   "62820" : null,
   "62850" : null,
   "62880" : null,
   "62910" : null,
   "62940" : null,
   "62970" : null,
   "630" : null,
   "6300" : null,
   "63000" : null,
   "63030" : null,
   "63060" : null,
   "63090" : null,
   "63120" : null,
   "63150" : null,
   "63180" : null,
   "63210" : null,
   "63240" : null,
   "63270" : null,
   "6330" : null,
   "63300" : null,
   "63330" : null,
   "63360" : null,
   "63390" : null,
   "63420" : null,
   "63450" : null,
   "63480" : null,
   "63510" : null,
   "63540" : null,
   "63570" : null,
   "6360" : null,
   "63600" : null,
   "63630" : null,
   "63660" : null,
   "63690" : null,
   "63720" : null,
   "63750" : null,
   "63780" : null,
   "63810" : null,
   "63840" : null,
   "63870" : null,
   "6390" : null,
   "63900" : null,
   "63930" : null,
   "63960" : null,
   "63990" : null,
   "64020" : null,
   "64050" : null,
   "64080" : null,
   "64110" : null,
   "64140" : null,
   "64170" : null,
   "6420" : null,
   "64200" : null,
   "64230" : null,
   "64260" : null,
   "64290" : null,
   "64320" : null,
   "64350" : null,
   "64380" : null,
   "64410" : null,
   "64440" : null,
   "64470" : null,
   "6450" : null,
   "64500" : null,
   "64530" : null,
   "64560" : null,
   "64590" : null,
   "64620" : null,
   "64650" : null,
   "64680" : null,
   "64710" : null,
   "64740" : null,
   "64770" : null,
   "6480" : null,
   "64800" : null,
   "64830" : null,
   "64860" : null,
   "64890" : null,
   "64920" : null,
   "64950" : null,
   "64980" : null,
   "65010" : null,
   "65040" : null,
   "65070" : null,
   "6510" : null,
   "65100" : null,
   "65130" : null,
   "65160" : null,
   "65190" : null,
   "65220" : null,
   "65250" : null,
   "65280" : null,
   "65310" : null,
   "65340" : null,
   "65370" : null,
   "6540" : null,
   "65400" : null,
   "65430" : null,
   "65460" : null,
   "65490" : null,
   "65520" : null,
   "65550" : null,
   "65580" : null,
   "65610" : null,
   "65640" : null,
   "65670" : null,
   "6570" : null,
   "65700" : null,
   "65730" : null,
   "65760" : null,
   "65790" : null,
   "65820" : null,
   "65850" : null,
   "65880" : null,
   "65910" : null,
   "65940" : null,
   "65970" : null,
   "660" : null,
   "6600" : null,
   "66000" : null,
   "66030" : null,
   "66060" : null,
   "66090" : null,
   "66120" : null,
   "66150" : null,
   "66180" : null,
   "66210" : null,
   "66240" : null,
   "66270" : null,
   "6630" : null,
   "66300" : null,
   "66330" : null,
   "66360" : null,
   "66390" : null,
   "66420" : null,
   "66450" : null,
   "66480" : null,
   "66510" : null,
   "66540" : null,
   "66570" : null,
   "6660" : null,
   "66600" : null,
   "66630" : null,
   "66660" : null,
   "66690" : null,
   "66720" : null,
   "66750" : null,
   "66780" : null,
   "66810" : null,
   "66840" : null,
   "66870" : null,
   "6690" : null,
   "66900" : null,
   "66930" : null,
   "66960" : null,
   "66990" : null,
   "67020" : null,
   "67050" : null,
   "67080" : null,
   "67110" : null,
   "67140" : null,
   "67170" : null,
   "6720" : null,
   "67200" : null,
   "67230" : null,
   "67260" : null,
   "67290" : null,
   "67320" : null,
   "67350" : null,
   "67380" : null,
   "67410" : null,
   "67440" : null,
   "67470" : null,
   "6750" : null,
   "67500" : null,
   "67530" : null,
   "67560" : null,
   "67590" : null,
   "67620" : null,
   "67650" : null,
   "67680" : null,
   "67710" : null,
   "67740" : null,
   "67770" : null,
   "6780" : null,
   "67800" : null,
   "67830" : null,
   "67860" : null,
   "67890" : null,
   "67920" : null,
   "67950" : null,
   "67980" : null,
   "68010" : null,
   "68040" : null,
   "68070" : null,
   "6810" : null,
   "68100" : null,
   "68130" : null,
   "68160" : null,
   "68190" : null,
   "68220" : null,
   "68250" : null,
   "68280" : null,
   "68310" : null,
   "68340" : null,
   "68370" : null,
   "6840" : null,
   "68400" : null,
   "68430" : null,
   "68460" : null,
   "68490" : null,
   "68520" : null,
   "68550" : null,
   "68580" : null,
   "68610" : null,
   "68640" : null,
   "68670" : null,
   "6870" : null,
   "68700" : null,
   "68730" : null,
   "68760" : null,
   "68790" : null,
   "68820" : null,
   "68850" : null,
   "68880" : null,
   "68910" : null,
   "68940" : null,
   "68970" : null,
   "690" : null,
   "6900" : null,
   "69000" : null,
   "69030" : null,
   "69060" : null,
   "69090" : null,
   "69120" : null,
   "69150" : null,
   "69180" : null,
   "69210" : null,
   "69240" : null,
   "69270" : null,
   "6930" : null,
   "69300" : null,
   "69330" : null,
   "69360" : null,
   "69390" : null,
   "69420" : null,
   "69450" : null,
   "69480" : null,
   "69510" : null,
   "69540" : null,
   "69570" : null,
   "6960" : null,
   "69600" : null,
   "69630" : null,
   "69660" : null,
   "69690" : null,
   "69720" : null,
   "69750" : null,
   "69780" : null,
   "69810" : null,
   "69840" : null,
   "69870" : null,
   "6990" : null,
   "69900" : null,
   "69930" : null,
   "69960" : null,
   "69990" : null,
   "70020" : null,
   "70050" : null,
   "70080" : null,
   "70110" : null,
   "70140" : null,
   "70170" : null,
   "7020" : null,
   "70200" : null,
   "70230" : null,
   "70260" : null,
   "70290" : null,
   "70320" : null,
   "70350" : null,
   "70380" : null,
   "70410" : null,
   "70440" : null,
   "70470" : null,
   "7050" : null,
   "70500" : null,
   "70530" : null,
   "70560" : null,
   "70590" : null,
   "70620" : null,
   "70650" : null,
   "70680" : null,
   "70710" : null,
   "70740" : null,
   "70770" : null,
   "7080" : null,
   "70800" : null,
   "70830" : null,
   "70860" : null,
   "70890" : null,
   "70920" : null,
   "70950" : null,
   "70980" : null,
   "71010" : null,
   "71040" : null,
   "71070" : null,
   "7110" : null,
   "71100" : null,
   "71130" : null,
   "71160" : null,
   "71190" : null,
   "71220" : null,
   "71250" : null,
   "71280" : null,
   "71310" : null,
   "71340" : null,
   "71370" : null,
   "7140" : null,
   "71400" : null,
   "71430" : null,
   "71460" : null,
   "71490" : null,
   "71520" : null,
   "71550" : null,
   "71580" : null,
   "71610" : null,
   "71640" : null,
   "71670" : null,
   "7170" : null,
   "71700" : null,
   "71730" : null,
   "71760" : null,
   "71790" : null,
   "71820" : null,
   "71850" : null,
   "71880" : null,
   "71910" : null,
   "71940" : null,
   "71970" : null,
   "720" : null,
   "7200" : null,
   "72000" : null,
   "72030" : null,
   "72060" : null,
   "72090" : null,
   "72120" : null,
   "72150" : null,
   "72180" : null,
   "72210" : null,
   "72240" : null,
   "72270" : null,
   "7230" : null,
   "72300" : null,
   "72330" : null,
   "72360" : null,
   "72390" : null,
   "72420" : null,
   "72450" : null,
   "72480" : null,
   "72510" : null,
   "72540" : null,
   "72570" : null,
   "7260" : null,
   "72600" : null,
   "72630" : null,
   "72660" : null,
   "72690" : null,
   "72720" : null,
   "72750" : null,
   "72780" : null,
   "72810" : null,
   "72840" : null,
   "72870" : null,
   "7290" : null,
   "72900" : null,
   "72930" : null,
   "72960" : null,
   "72990" : null,
   "73020" : null,
   "73050" : null,
   "73080" : null,
   "73110" : null,
   "73140" : null,
   "73170" : null,
   "7320" : null,
   "73200" : null,
   "73230" : null,
   "73260" : null,
   "73290" : null,
   "73320" : null,
   "73350" : null,
   "73380" : null,
   "73410" : null,
   "73440" : null,
   "73470" : null,
   "7350" : null,
   "73500" : null,
   "73530" : null,
   "73560" : null,
   "73590" : null,
   "73620" : null,
   "73650" : null,
   "73680" : null,
   "73710" : null,
   "73740" : null,
   "73770" : null,
   "7380" : null,
   "73800" : null,
   "73830" : null,
   "73860" : null,
   "73890" : null,
   "73920" : null,
   "73950" : null,
   "73980" : null,
   "74010" : null,
   "74040" : null,
   "74070" : null,
   "7410" : null,
   "74100" : null,
   "74130" : null,
   "74160" : null,
   "74190" : null,
   "74220" : null,
   "74250" : null,
   "74280" : null,
   "74310" : null,
   "74340" : null,
   "74370" : null,
   "7440" : null,
   "74400" : null,
   "74430" : null,
   "74460" : null,
   "74490" : null,
   "74520" : null,
   "74550" : null,
   "74580" : null,
   "74610" : null,
   "74640" : null,
   "74670" : null,
   "7470" : null,
   "74700" : null,
   "74730" : null,
   "74760" : null,
   "74790" : null,
   "74820" : null,
   "74850" : null,
   "74880" : null,
   "74910" : null,
   "74940" : null,
   "74970" : null,
   "750" : null,
   "7500" : null,
   "75000" : null,
   "75030" : null,
   "75060" : null,
   "75090" : null,
   "75120" : null,
   "75150" : null,
   "75180" : null,
   "75210" : null,
   "75240" : null,
   "75270" : null,
   "7530" : null,
   "75300" : null,
   "75330" : null,
   "75360" : null,
   "75390" : null,
   "75420" : null,
   "75450" : null,
   "75480" : null,
   "75510" : null,
   "75540" : null,
   "75570" : null,
   "7560" : null,
   "75600" : null,
   "75630" : null,
   "75660" : null,
   "75690" : null,
   "75720" : null,
   "75750" : null,
   "75780" : null,
   "75810" : null,
   "75840" : null,
   "75870" : null,
   "7590" : null,
   "75900" : null,
   "75930" : null,
   "75960" : null,
   "75990" : null,
   "76020" : null,
   "76050" : null,
   "76080" : null,
   "76110" : null,
   "76140" : null,
   "76170" : null,
   "7620" : null,
   "76200" : null,
   "76230" : null,
   "76260" : null,
   "76290" : null,
   "76320" : null,
   "76350" : null,
   "76380" : null,
   "76410" : null,
   "76440" : null,
   "76470" : null,
   "7650" : null,
   "76500" : null,
   "76530" : null,
   "76560" : null,
   "76590" : null,
   "76620" : null,
   "76650" : null,
   "76680" : null,
   "76710" : null,
   "76740" : null,
   "76770" : null,
   "7680" : null,
   "76800" : null,
   "76830" : null,
   "76860" : null,
   "76890" : null,
   "76920" : null,
   "76950" : null,
   "76980" : null,
   "77010" : null,
   "77040" : null,
   "77070" : null,
   "7710" : null,
   "77100" : null,
   "77130" : null,
   "77160" : null,
   "77190" : null,
   "77220" : null,
   "77250" : null,
   "77280" : null,
   "77310" : null,
   "77340" : null,
   "77370" : null,
   "7740" : null,
   "77400" : null,
   "77430" : null,
   "77460" : null,
   "77490" : null,
   "77520" : null,
   "77550" : null,
   "77580" : null,
   "77610" : null,
   "77640" : null,
   "77670" : null,
   "7770" : null,
   "77700" : null,
   "77730" : null,
   "77760" : null,
   "77790" : null,
   "77820" : null,
   "77850" : null,
   "77880" : null,
   "77910" : null,
   "77940" : null,
   "77970" : null,
   "780" : null,
   "7800" : null,
   "78000" : null,
   "78030" : null,
   "78060" : null,
   "78090" : null,
   "78120" : null,
   "78150" : null,
   "78180" : null,
   "78210" : null,
   "78240" : null,
   "78270" : null,
   "7830" : null,
   "78300" : null,
   "78330" : null,
   "78360" : null,
   "78390" : null,
   "78420" : null,
   "78450" : null,
   "78480" : null,
   "78510" : null,
   "78540" : null,
   "78570" : null,
   "7860" : null,
   "78600" : null,
   "78630" : null,
   "78660" : null,
   "78690" : null,
   "78720" : null,
   "78750" : null,
   "78780" : null,
   "78810" : null,
   "78840" : null,
   "78870" : null,
   "7890" : null,
   "78900" : null,
   "78930" : null,
   "78960" : null,
   "78990" : null,
   "79020" : null,
   "79050" : null,
   "79080" : null,
   "79110" : null,
   "79140" : null,
   "79170" : null,
   "7920" : null,
   "79200" : null,
   "79230" : null,
   "79260" : null,
   "79290" : null,
   "79320" : null,
   "79350" : null,
   "79380" : null,
   "79410" : null,
   "79440" : null,
   "79470" : null,
   "7950" : null,
   "79500" : null,
   "79530" : null,
   "79560" : null,
   "79590" : null,
   "79620" : null,
   "79650" : null,
   "79680" : null,
   "79710" : null,
   "79740" : null,
   "79770" : null,
   "7980" : null,
   "79800" : null,
   "79830" : null,
   "79860" : null,
   "79890" : null,
   "79920" : null,
   "79950" : null,
   "79980" : null,
   "80010" : null,
   "80040" : null,
   "80070" : null,
   "8010" : null,
   "80100" : null,
   "80130" : null,
   "80160" : null,
   "80190" : null,
   "80220" : null,
   "80250" : null,
   "80280" : null,
   "80310" : null,
   "80340" : null,
   "80370" : null,
   "8040" : null,
   "80400" : null,
   "80430" : null,
   "80460" : null,
   "80490" : null,
   "80520" : null,
   "80550" : null,
   "80580" : null,
   "80610" : null,
   "80640" : null,
   "80670" : null,
   "8070" : null,
   "80700" : null,
   "80730" : null,
   "80760" : null,
   "80790" : null,
   "80820" : null,
   "80850" : null,
   "80880" : null,
   "80910" : null,
   "80940" : null,
   "80970" : null,
   "810" : null,
   "8100" : null,
   "81000" : null,
   "81030" : null,
   "81060" : null,
   "81090" : null,
   "81120" : null,
   "81150" : null,
   "81180" : null,
   "81210" : null,
   "81240" : null,
   "81270" : null,
   "8130" : null,
   "81300" : null,
   "81330" : null,
   "81360" : null,
   "81390" : null,
   "81420" : null,
   "81450" : null,
   "81480" : null,
   "81510" : null,
   "81540" : null,
   "81570" : null,
   "8160" : null,
   "81600" : null,
   "81630" : null,
   "81660" : null,
   "81690" : null,
   "81720" : null,
   "81750" : null,
   "81780" : null,
   "81810" : null,
   "81840" : null,
   "81870" : null,
   "8190" : null,
   "81900" : null,
   "81930" : null,
   "81960" : null,
   "81990" : null,
   "82020" : null,
   "82050" : null,
   "82080" : null,
   "82110" : null,
   "82140" : null,
   "82170" : null,
   "8220" : null,
   "82200" : null,
   "82230" : null,
   "82260" : null,
   "82290" : null,
   "82320" : null,
   "82350" : null,
   "82380" : null,
   "82410" : null,
   "82440" : null,
   "82470" : null,
   "8250" : null,
   "82500" : null,
   "82530" : null,
   "82560" : null,
   "82590" : null,
   "82620" : null,
   "82650" : null,
   "82680" : null,
   "82710" : null,
   "82740" : null,
   "82770" : null,
   "8280" : null,
   "82800" : null,
   "82830" : null,
   "82860" : null,
   "82890" : null,
   "82920" : null,
   "82950" : null,
   "82980" : null,
   "83010" : null,
   "83040" : null,
   "83070" : null,
   "8310" : null,
   "83100" : null,
   "83130" : null,
   "83160" : null,
   "83190" : null,
   "83220" : null,
   "83250" : null,
   "83280" : null,
   "83310" : null,
   "83340" : null,
   "83370" : null,
   "8340" : null,
   "83400" : null,
   "83430" : null,
   "83460" : null,
   "83490" : null,
   "83520" : null,
   "83550" : null,
   "83580" : null,
   "83610" : null,
   "83640" : null,
   "83670" : null,
   "8370" : null,
   "83700" : null,
   "83730" : null,
   "83760" : null,
   "83790" : null,
   "83820" : null,
   "83850" : null,
   "83880" : null,
   "83910" : null,
   "83940" : null,
   "83970" : null,
   "840" : null,
   "8400" : null,
   "84000" : null,
   "84030" : null,
   "84060" : null,
   "84090" : null,
   "84120" : null,
   "84150" : null,
   "84180" : null,
   "84210" : null,
   "84240" : null,
   "84270" : null,
   "8430" : null,
   "84300" : null,
   "84330" : null,
   "84360" : null,
   "84390" : null,
   "84420" : null,
   "84450" : null,
   "84480" : null,
   "84510" : null,
   "84540" : null,
   "84570" : null,
   "8460" : null,
   "84600" : null,
   "84630" : null,
   "84660" : null,
   "84690" : null,
   "84720" : null,
   "84750" : null,
   "84780" : null,
   "84810" : null,
   "84840" : null,
   "84870" : null,
   "8490" : null,
   "84900" : null,
   "84930" : null,
   "84960" : null,
   "84990" : null,
   "85020" : null,
   "85050" : null,
   "85080" : null,
   "85110" : null,
   "85140" : null,
   "85170" : null,
   "8520" : null,
   "85200" : null,
   "85230" : null,
   "85260" : null,
   "85290" : null,
   "85320" : null,
   "85350" : null,
   "85380" : null,
   "85410" : null,
   "85440" : null,
   "85470" : null,
   "8550" : null,
   "85500" : null,
   "85530" : null,
   "85560" : null,
   "85590" : null,
   "85620" : null,
   "85650" : null,
   "85680" : null,
   "85710" : null,
   "85740" : null,
   "85770" : null,
   "8580" : null,
   "85800" : null,
   "85830" : null,
   "85860" : null,
   "85890" : null,
   "85920" : null,
   "85950" : null,
   "85980" : null,
   "86010" : null,
   "86040" : null,
   "86070" : null,
   "8610" : null,
   "86100" : null,
   "86130" : null,
   "86160" : null,
   "86190" : null,
   "86220" : null,
   "86250" : null,
   "86280" : null,
   "86310" : null,
   "86340" : null,
   "86370" : null,
   "8640" : null,
   "86400" : null,
   "8670" : null,
   "870" : null,
   "8700" : null,
   "8730" : null,
   "8760" : null,
   "8790" : null,
   "8820" : null,
   "8850" : null,
   "8880" : null,
   "8910" : null,
   "8940" : null,
   "8970" : null,
   "90" : null,
   "900" : null,
   "9000" : null,
   "9030" : null,
   "9060" : null,
   "9090" : null,
   "9120" : null,
   "9150" : null,
   "9180" : null,
   "9210" : null,
   "9240" : null,
   "9270" : null,
   "930" : null,
   "9300" : null,
   "9330" : null,
   "9360" : null,
   "9390" : null,
   "9420" : null,
   "9450" : null,
   "9480" : null,
   "9510" : null,
   "9540" : null,
   "9570" : null,
   "960" : null,
   "9600" : null,
   "9630" : null,
   "9660" : null,
   "9690" : null,
   "9720" : null,
   "9750" : null,
   "9780" : null,
   "9810" : null,
   "9840" : null,
   "9870" : null,
   "990" : null,
   "9900" : null,
   "9930" : null,
   "9960" : null,
   "9990" : null,
   "Metadata" : {
      "above_RangeA_Count" : {
         "index" : 21,
         "units" : ""
      },
      "above_RangeA_Duration" : {
         "index" : 20,
         "units" : "s"
      },
      "above_RangeB_Count" : {
         "index" : 25,
         "units" : ""
      },
      "above_RangeB_Duration" : {
         "index" : 24,
         "units" : "s"
      },
      "below_10_percent_NormVol_Count" : {
         "index" : 29,
         "units" : ""
      },
      "below_10_percent_NormVol_Duration" : {
         "index" : 28,
         "units" : "s"
      },
      "below_RangeA_Count" : {
         "index" : 23,
         "units" : ""
      },
      "below_RangeA_Duration" : {
         "index" : 22,
         "units" : "s"
      },
      "below_RangeB_Count" : {
         "index" : 27,
         "units" : ""
      },
      "below_RangeB_Duration" : {
         "index" : 26,
         "units" : "s"
      },
      "bill" : {
         "index" : 10,
         "units" : "USD"
      },
      "reactive_energy" : {
         "index" : 9,
         "units" : "VARh"
      },
      "reactive_power_avg" : {
         "index" : 6,
         "units" : "VAR"
      },
      "reactive_power_max" : {
         "index" : 5,
         "units" : "VAR"
      },
      "reactive_power_median" : {
         "index" : 7,
         "units" : "VAR"
      },
      "reactive_power_min" : {
         "index" : 4,
         "units" : "VAR"
      },
      "real_energy" : {
         "index" : 8,
         "units" : "Wh"
      },
      "real_power_avg" : {
         "index" : 2,
         "units" : "W"
      },
      "real_power_max" : {
         "index" : 1,
         "units" : "W"
      },
      "real_power_median" : {
         "index" : 3,
         "units" : "W"
      },
      "real_power_min" : {
         "index" : 0,
         "units" : "W"
      },
      "voltage12_avg" : {
         "index" : 13,
         "units" : "V"
      },
      "voltage12_max" : {
         "index" : 12,
         "units" : "V"
      },
      "voltage12_min" : {
         "index" : 11,
         "units" : "V"
      },
      "voltage_avg" : {
         "index" : 16,
         "units" : "V"
      },
      "voltage_max" : {
         "index" : 15,
         "units" : "V"
      },
      "voltage_min" : {
         "index" : 14,
         "units" : "V"
      },
      "voltage_unbalance_avg" : {
         "index" : 19,
         "units" : "V"
      },
      "voltage_unbalance_max" : {
         "index" : 18,
         "units" : "V"
      },
      "voltage_unbalance_min" : {
         "index" : 17,
         "units" : "V"
      }
   },
   "StartTime" : "2010-08-16 00:00:00 UTC"
}

